orhelper/__init__.py
orhelper/_enums.py
orhelper/_orhelper.py
orhelper-0.1.3.dist-info/LICENSE
orhelper-0.1.3.dist-info/METADATA
orhelper-0.1.3.dist-info/WHEEL
orhelper-0.1.3.dist-info/top_level.txt
orhelper-0.1.3.dist-info/RECORD
