Metadata-Version: 2.1
Name: orhelper
Version: 0.1.3
Summary: OrHelper is a module which aims to facilitate interacting and scripting with OpenRocket from Python.
Home-page: https://github.com/SilentSys/orhelper
Author: Andrei Popescu
Author-email: Popescu.Andrei.David@gmail.com
License: UNKNOWN
Platform: UNKNOWN
Requires-Python: >=3.6
Requires-Dist: jpype1 (>=0.6.3)
Requires-Dist: numpy
